setproctitle/__init__.py
setproctitle/_setproctitle.cpython-313-powerpc64le-linux-gnu.so
setproctitle/py.typed
setproctitle-1.3.7.dist-info/METADATA
setproctitle-1.3.7.dist-info/WHEEL
setproctitle-1.3.7.dist-info/top_level.txt
setproctitle-1.3.7.dist-info/RECORD
setproctitle-1.3.7.dist-info/licenses/LICENSE
