Metadata-Version: 2.1
Name: setproctitle
Version: 1.3.7
Summary: A Python module to customize the process title
Home-page: https://github.com/dvarrazzo/py-setproctitle
Download-URL: http://pypi.python.org/pypi/setproctitle/
Author: Daniele Varrazzo
Author-email: daniele.varrazzo@gmail.com
License: BSD-3-Clause
Platform: GNU/Linux
Platform: BSD
Platform: MacOS X
Platform: Windows
Classifier: Development Status :: 5 - Production/Stable
Classifier: Intended Audience :: Developers
Classifier: License :: OSI Approved :: BSD License
Classifier: Programming Language :: C
Classifier: Programming Language :: Python :: 3
Classifier: Programming Language :: Python :: 3.8
Classifier: Programming Language :: Python :: 3.9
Classifier: Programming Language :: Python :: 3.10
Classifier: Programming Language :: Python :: 3.11
Classifier: Programming Language :: Python :: 3.12
Classifier: Programming Language :: Python :: 3.13
Classifier: Programming Language :: Python :: 3.14
Classifier: Operating System :: POSIX :: Linux
Classifier: Operating System :: POSIX :: BSD
Classifier: Operating System :: MacOS :: MacOS X
Classifier: Operating System :: Microsoft :: Windows
Classifier: Topic :: Software Development
Requires-Python: >=3.8
License-File: LICENSE
Provides-Extra: test
Requires-Dist: pytest ; extra == 'test'
